Workbook

Sheet Resumen
A1: RESUMEN DE AVANCE - SISTEMA POS Y TIENDA EN LÍNEA DE LAMBRÍN
A4: INDICADORES FASE 1 | D4: INDICADORES FASE 2
A5: Total de criterios | B5: ='Fase 1'!B5 -> 77 | D5: Total de criterios | E5: ='Fase 2'!B5 -> 21
A6: Cumple | B6: ='Fase 1'!B6 -> 1 | D6: Cumple | E6: ='Fase 2'!B6 -> 0
A7: Parcial | B7: ='Fase 1'!B7 -> 0 | D7: Parcial | E7: ='Fase 2'!B7 -> 0
A8: No cumple | B8: ='Fase 1'!B8 -> 0 | D8: No cumple | E8: ='Fase 2'!B8 -> 0
A9: En revisión | B9: ='Fase 1'!B9 -> 0 | D9: En revisión | E9: ='Fase 2'!B9 -> 0
A10: Bloqueado | B10: ='Fase 1'!B10 -> 0 | D10: Bloqueado | E10: ='Fase 2'!B10 -> 0
A11: Pendiente | B11: ='Fase 1'!B11 -> 76 | D11: Pendiente | E11: ='Fase 2'!B11 -> 21
A12: Avance efectivo | B12: ='Fase 1'!B12 -> 0.012987013 | D12: Avance efectivo | E12: ='Fase 2'!B12 -> 0
A15: Uso rápido
A16: 1. Trabaja en las hojas Fase 1 o Fase 2; cada una tiene sus propios indicadores.
A17: 2. Responsable ofrece Aaron, David o Mantenimiento.
A18: 3. Fecha validación ofrece fechas rápidas desde 15 días atrás hasta 15 días adelante.
A19: 4. Para obtener un PDF actualizado después de marcar: Archivo > Exportar/Guardar como > PDF.
A20: 5. La hoja Transversales y entrega conserva seguridad, arquitectura y entregables fuera de una fase única.

Sheet Fase 1
A1: CHECKLIST - FASE 1: PUNTO DE VENTA
A4: Indicador | B4: Valor
A5: Total de criterios | B5: =COUNTA($A$15:$A$91) -> 77
A6: Cumple | B6: =COUNTIF($I$15:$I$91,"Cumple") -> 1
A7: Parcial | B7: =COUNTIF($I$15:$I$91,"Parcial") -> 0
A8: No cumple | B8: =COUNTIF($I$15:$I$91,"No cumple") -> 0
A9: En revisión | B9: =COUNTIF($I$15:$I$91,"En revisión") -> 0
A10: Bloqueado | B10: =COUNTIF($I$15:$I$91,"Bloqueado") -> 0
A11: Pendiente | B11: =COUNTIF($I$15:$I$91,"Pendiente") -> 76
A12: Avance efectivo | B12: =IF(B5=0,0,(B6+B7*0.5)/B5) -> 0.012987013
A14: ID | B14: Fase | C14: Módulo | D14: Tipo de prueba | E14: Requisito / criterio | F14: Cómo validarlo | G14: Resultado esperado | H14: Prioridad | I14: Estado | J14: Evidencia / enlace | K14: Incidencia | L14: Responsable | M14: Fecha validación | N14: Fuente
A15: CHK-001 | B15: Fase 1 | C15: Login | D15: Funcional | E15: El usuario puede iniciar sesión con credenciales válidas | F15: Probar usuario activo con contraseña correcta | G15: Acceso permitido y sesión creada | H15: Crítica | I15: Cumple | L15: Aaron | M15: 46238 | N15: Propuesta PDF
A16: CHK-002 | B16: Fase 1 | C16: Login | D16: Negativa | E16: Rechazo de credenciales inválidas | F16: Probar contraseña incorrecta y usuario inexistente | G16: No permite acceso y muestra mensaje seguro | H16: Crítica | I16: Pendiente | N16: Validación técnica recomendada
A17: CHK-003 | B17: Fase 1 | C17: Login | D17: Seguridad | E17: Control de intentos y cierre de sesión | F17: Forzar intentos fallidos; cerrar sesión y reutilizar URL | G17: Sesión invalidada; no expone datos sensibles | H17: Alta | I17: Pendiente | N17: Validación técnica recomendada
A18: CHK-004 | B18: Fase 1 | C18: Login | D18: Seguridad | E18: Rutas protegidas según autenticación | F18: Abrir rutas internas sin sesión o con token vencido | G18: Redirige a login o responde 401 | H18: Crítica | I18: Pendiente | N18: Validación técnica recomendada
A19: CHK-005 | B19: Fase 1 | C19: Empleados | D19: CRUD | E19: Alta, consulta, edición y baja lógica de empleados | F19: Crear empleado, editarlo, consultarlo y desactivarlo | G19: Cambios persistidos; el histórico no se pierde | H19: Alta | I19: Pendiente | N19: Propuesta PDF
A20: CHK-006 | B20: Fase 1 | C20: Empleados | D20: Validación | E20: Datos obligatorios y duplicados | F20: Omitir campos requeridos y repetir identificador/correo | G20: Bloquea datos inválidos con mensajes claros | H20: Alta | I20: Pendiente | N20: Validación técnica recomendada
A21: CHK-007 | B21: Fase 1 | C21: Empleados | D21: Integración | E21: Empleado vinculado con usuario, rol y bitácora | F21: Asignar rol y revisar registro de cambios | G21: Acceso coincide con rol y queda auditado | H21: Alta | I21: Pendiente | N21: Propuesta PDF
A22: CHK-008 | B22: Fase 1 | C22: Roles y permisos | D22: CRUD | E22: Administración de roles y permisos por módulo | F22: Crear rol y asignar consultar/crear/editar/eliminar/aprobar/exportar | G22: Permisos guardados y visibles | H22: Crítica | I22: Pendiente | N22: Propuesta PDF
A23: CHK-009 | B23: Fase 1 | C23: Roles y permisos | D23: Seguridad | E23: La API aplica permisos, no solo la interfaz | F23: Invocar endpoint restringido con usuario sin permiso | G23: API responde 403 y no altera datos | H23: Crítica | I23: Pendiente | N23: Validación técnica recomendada
A24: CHK-010 | B24: Fase 1 | C24: Roles y permisos | D24: Regla | E24: Permisos especiales para descuentos, precios, cancelaciones y devoluciones | F24: Probar cada operación con y sin privilegio | G24: Solo roles autorizados completan la operación | H24: Crítica | I24: Pendiente | N24: Propuesta PDF
A25: CHK-011 | B25: Fase 1 | C25: Panel principal y POS | D25: Funcional | E25: Panel muestra indicadores operativos útiles | F25: Comparar indicadores con ventas, caja e inventario de prueba | G25: Totales y estados coinciden con datos origen | H25: Media | I25: Pendiente | N25: Propuesta PDF / validar definición con cliente
A26: CHK-012 | B26: Fase 1 | C26: Panel principal y POS | D26: Venta | E26: Carrito agrega, modifica y elimina productos | F26: Agregar varios productos, cambiar cantidad y retirar uno | G26: Subtotales y total se recalculan correctamente | H26: Crítica | I26: Pendiente | N26: Propuesta PDF
A27: CHK-013 | B27: Fase 1 | C27: Panel principal y POS | D27: Hardware | E27: Escaneo con pistola USB | F27: Escanear códigos existentes, repetidos e inexistentes | G27: Agrega producto correcto; maneja códigos inválidos | H27: Alta | I27: Pendiente | N27: Propuesta PDF
... A91: CHK-077 | B91: Fase 1 | C91: Reportes generales | D91: Rendimiento | E91: Reportes responden con volumen realista | F91: Cargar datos de prueba y medir consultas | G91: Tiempo aceptable acordado; no bloquea operación | H91: Media | I91: Pendiente | N91: Validación técnica recomendada

Sheet Fase 2
A1: CHECKLIST - FASE 2: TIENDA EN LÍNEA Y ATENCIÓN
A4: Indicador | B4: Valor
A5: Total de criterios | B5: =COUNTA($A$15:$A$35) -> 21
A6: Cumple | B6: =COUNTIF($I$15:$I$35,"Cumple") -> 0
A7: Parcial | B7: =COUNTIF($I$15:$I$35,"Parcial") -> 0
A8: No cumple | B8: =COUNTIF($I$15:$I$35,"No cumple") -> 0
A9: En revisión | B9: =COUNTIF($I$15:$I$35,"En revisión") -> 0
A10: Bloqueado | B10: =COUNTIF($I$15:$I$35,"Bloqueado") -> 0
A11: Pendiente | B11: =COUNTIF($I$15:$I$35,"Pendiente") -> 21
A12: Avance efectivo | B12: =IF(B5=0,0,(B6+B7*0.5)/B5) -> 0
A14: ID | B14: Fase | C14: Módulo | D14: Tipo de prueba | E14: Requisito / criterio | F14: Cómo validarlo | G14: Resultado esperado | H14: Prioridad | I14: Estado | J14: Evidencia / enlace | K14: Incidencia | L14: Responsable | M14: Fecha validación | N14: Fuente
A15: CHK-078 | B15: Fase 2 | C15: Tienda en línea | D15: UI | E15: Página pública responsiva de productos y categorías | F15: Probar computadora, tableta y móvil | G15: Navegación usable sin desbordes | H15: Alta | I15: Pendiente | N15: Propuesta PDF
A16: CHK-079 | B16: Fase 2 | C16: Tienda en línea | D16: Catálogo | E16: Buscador, filtros, fichas, imágenes y disponibilidad | F16: Buscar y filtrar casos conocidos | G16: Resultados y stock coinciden con sistema interno | H16: Alta | I16: Pendiente | N16: Propuesta PDF
A17: CHK-080 | B17: Fase 2 | C17: Tienda en línea | D17: Regla | E17: Distingue compra directa y solo cotización | F17: Abrir productos de ambas modalidades | G17: Solo permite la acción configurada | H17: Crítica | I17: Pendiente | N17: Propuesta PDF
A18: CHK-081 | B18: Fase 2 | C18: Carrito web | D18: Cálculo | E18: Cantidades, subtotales, descuentos y total | F18: Modificar cantidades y promociones | G18: Cálculo coincide con POS y reglas centrales | H18: Crítica | I18: Pendiente | N18: Propuesta PDF
A19: CHK-082 | B19: Fase 2 | C19: Carrito web | D19: Persistencia | E19: Carrito conserva estado conforme a diseño acordado | F19: Actualizar página/iniciar sesión/cambiar dispositivo según alcance | G19: Comportamiento coincide con definición | H19: Media | I19: Pendiente | N19: Propuesta PDF / validar definición con cliente
A20: CHK-083 | B20: Fase 2 | C20: Cuenta de cliente | D20: Seguridad | E20: Registro, login y recuperación de cuenta | F20: Probar alta, duplicado, acceso y recuperación | G20: Flujos seguros y mensajes correctos | H20: Crítica | I20: Pendiente | N20: Propuesta PDF
A21: CHK-084 | B21: Fase 2 | C21: Cuenta de cliente | D21: Funcional | E21: Direcciones, historial y seguimiento de envíos | F21: Guardar direcciones y consultar pedidos | G21: Información propia, actualizada y aislada por cliente | H21: Alta | I21: Pendiente | N21: Propuesta PDF
A22: CHK-085 | B22: Fase 2 | C22: Integración web-POS | D22: Integración | E22: Productos, inventario, clientes, pedidos, anticipos y pagos comparten datos | F22: Crear pedido web y revisar operación interna | G22: Sincronización sin duplicados ni stock negativo | H22: Crítica | I22: Pendiente | N22: Propuesta PDF
A23: CHK-086 | B23: Fase 2 | C23: Pagos externos | D23: Alcance | E23: Preparación para métodos de pago y servicios externos | F23: Revisar interfaces/configuración sin asumir proveedor incluido | G23: Arquitectura extensible; proveedor queda fuera del precio | H23: Media | I23: Pendiente | N23: Propuesta PDF
A24: CHK-087 | B24: Fase 2 | C24: Atención al cliente | D24: Tickets | E24: Creación de tickets por empleados y clientes | F24: Crear ticket desde ambos canales | G24: Folio, origen y cliente correctos | H24: Alta | I24: Pendiente | N24: Propuesta PDF
A25: CHK-088 | B25: Fase 2 | C25: Atención al cliente | D25: Clasificación | E25: Clasificación por producto, sistema, pedidos, cotizaciones, devoluciones y entrega | F25: Crear casos de cada categoría | G25: Categoría y vínculo se guardan | H25: Alta | I25: Pendiente | N25: Propuesta PDF
A26: CHK-089 | B26: Fase 2 | C26: Atención al cliente | D26: Estados | E26: Nuevo, En proceso, Pendiente de respuesta, Resuelto, Cerrado y Reabierto | F26: Recorrer transiciones válidas e inválidas | G26: Estado e historial cumplen flujo | H26: Crítica | I26: Pendiente | N26: Propuesta PDF
... A35: CHK-098 | B35: Fase 2 | C35: Atención al cliente | D35: Bitácora | E35: Creación, respuestas, cambios de estado y cierre son inmodificables | F35: Ejecutar flujo completo y revisar auditoría | G35: Historial completo e inalterable | H35: Crítica | I35: Pendiente | N35: Propuesta PDF

Sheet Transversales y entrega
A1: CHECKLIST - CRITERIOS TRANSVERSALES Y ENTREGA
A4: Indicador | B4: Valor
A5: Total de criterios | B5: =COUNTA($A$15:$A$45) -> 31
A6: Cumple | B6: =COUNTIF($I$15:$I$45,"Cumple") -> 0
A7: Parcial | B7: =COUNTIF($I$15:$I$45,"Parcial") -> 0
A8: No cumple | B8: =COUNTIF($I$15:$I$45,"No cumple") -> 0
A9: En revisión | B9: =COUNTIF($I$15:$I$45,"En revisión") -> 0
A10: Bloqueado | B10: =COUNTIF($I$15:$I$45,"Bloqueado") -> 0
A11: Pendiente | B11: =COUNTIF($I$15:$I$45,"Pendiente") -> 31
A12: Avance efectivo | B12: =IF(B5=0,0,(B6+B7*0.5)/B5) -> 0
A14: ID | B14: Fase | C14: Módulo | D14: Tipo de prueba | E14: Requisito / criterio | F14: Cómo validarlo | G14: Resultado esperado | H14: Prioridad | I14: Estado | J14: Evidencia / enlace | K14: Incidencia | L14: Responsable | M14: Fecha validación | N14: Fuente
A15: CHK-099 | B15: Ambas | C15: Interfaz y compatibilidad | D15: Responsividad | E15: React adaptable a computadora, tableta y móvil | F15: Probar resoluciones y navegadores objetivo | G15: Sin controles cortados ni flujos inaccesibles | H15: Alta | I15: Pendiente | N15: Propuesta PDF
A16: CHK-100 | B16: Ambas | C16: Idiomas | D16: Localización | E16: Interfaz en español y chino simplificado | F16: Cambiar idioma y recorrer módulos principales | G16: Textos, validaciones, PDFs y plantillas traducidos | H16: Alta | I16: Pendiente | N16: Propuesta PDF
A17: CHK-101 | B17: Ambas | C17: Idiomas | D17: Persistencia | E17: Cambio de idioma se conserva según usuario/sesión | F17: Cambiar idioma, recargar y volver a entrar | G17: Preferencia se mantiene según diseño | H17: Media | I17: Pendiente | N17: Validación técnica recomendada
A18: CHK-102 | B18: Ambas | C18: Moneda | D18: Cálculo | E18: MXN como moneda principal y preparación para otras monedas | F18: Revisar modelo, formatos y cálculos | G18: MXN consistente; no hay símbolos/decimales erróneos | H18: Alta | I18: Pendiente | N18: Propuesta PDF
A19: CHK-103 | B19: Ambas | C19: API .NET 9 | D19: Arquitectura | E19: Backend ASP.NET Core .NET 9 con API REST | F19: Revisar archivos de proyecto, endpoints y ejecución | G19: Compila en .NET 9 y expone contrato REST coherente | H19: Crítica | I19: Pendiente | N19: Propuesta PDF
A20: CHK-104 | B20: Ambas | C20: API .NET 9 | D20: Calidad | E20: DTOs, validación, manejo global de errores, DI y operaciones async | F20: Revisión de código y pruebas de endpoints inválidos | G20: Sin exponer trazas; respuestas consistentes y código mantenible | H20: Alta | I20: Pendiente | N20: Validación técnica recomendada / antecedente de prompt no recuperado
A21: CHK-105 | B21: Ambas | C21: API .NET 9 | D21: Documentación | E21: API documentada y probada con OpenAPI/Swagger | F21: Abrir especificación y ejecutar operaciones | G21: Endpoints, modelos, códigos y autenticación documentados | H21: Alta | I21: Pendiente | N21: Validación técnica recomendada / antecedente de prompt no recuperado
A22: CHK-106 | B22: Ambas | C22: SQL Server | D22: Integridad | E22: Esquema, llaves, relaciones e índices soportan reglas | F22: Revisar modelo y ejecutar pruebas de integridad | G22: No hay huérfanos, duplicados críticos ni consultas sin soporte | H22: Crítica | I22: Pendiente | N22: Validación técnica recomendada
A23: CHK-107 | B23: Ambas | C23: SQL Server | D23: Migración | E23: Scripts crean y actualizan la base de forma repetible | F23: Ejecutar en BD limpia y actualizar una versión previa | G23: Instalación termina sin pasos ocultos ni pérdida de datos | H23: Crítica | I23: Pendiente | N23: Propuesta PDF
A24: CHK-108 | B24: Ambas | C24: Seguridad | D24: Credenciales | E24: Contraseñas cifradas con hash y secretos fuera del código | F24: Revisar BD, repositorio y configuración | G24: No hay contraseñas legibles ni secretos versionados | H24: Crítica | I24: Pendiente | N24: Validación técnica recomendada
A25: CHK-109 | B25: Ambas | C25: Seguridad | D25: Entradas | E25: Protección contra inyección, XSS, archivos peligrosos y acceso horizontal | F25: Ejecutar pruebas negativas representativas | G25: Entradas saneadas y acceso denegado correctamente | H25: Crítica | I25: Pendiente | N25: Validación técnica recomendada
A26: CHK-110 | B26: Ambas | C26: Seguridad | D26: Transporte | E26: Uso de HTTPS y políticas de origen/configuración adecuadas | F26: Revisar despliegue y llamadas del navegador | G26: Tráfico protegido y CORS limitado a orígenes autorizados | H26: Alta | I26: Pendiente | N26: Validación técnica recomendada
... A45: CHK-129 | B45: Entrega | C45: Aceptación | D45: Pagos | E45: 40% inicio, 30% entrega Fase 1 y 30% entrega Fase 2 | F45: Revisar hitos contra actas de aceptación | G45: Pagos ligados a entregables acordados | H45: Alta | I45: Pendiente | N45: Propuesta PDF

Sheet Guía de validación
A1: MÉTODO PARA COMPARAR ALCANCE VS. DESARROLLO
A4: Paso | B4: Qué revisar | C4: Frontend React | D4: API .NET 9 | E4: SQL Server | F4: Evidencia mínima
A5: 1 | B5: Trazabilidad del requisito | C5: Pantalla/ruta/componente | D5: Endpoint y DTO | E5: Tabla/SP/índice | F5: ID del checklist + referencia de código
A6: 2 | B6: Camino feliz | C6: Acción completa sin error | D6: 200/201 y respuesta correcta | E6: Datos persistidos | F6: Video/capturas + request/response
A7: 3 | B7: Validaciones | C7: Mensajes y campos | D7: 400 con errores claros | E7: Restricciones coherentes | F7: Caso negativo reproducible
A8: 4 | B8: Permisos y seguridad | C8: Oculta/deshabilita acciones | D8: 401/403 obligatorio | E8: Sin cambios no autorizados | F8: Usuario/rol + respuesta API
A9: 5 | B9: Integraciones | C9: Actualiza vistas relacionadas | D9: Transacción entre servicios | E9: Saldos y relaciones consistentes | F9: Consulta antes/después
A10: 6 | B10: Auditoría | C10: Historial visible cuando aplique | D10: Registra actor y cambio | E10: Bitácora inmutable | F10: Registro con valores antes/después
A11: 7 | B11: Regresión y aceptación | C11: Flujos anteriores siguen operando | D11: Suite sin fallos | E11: Migración reproducible | F11: Resultado final y aprobación
A13: Definición recomendada de terminado por módulo
A14: • Todos los criterios críticos y altos están en Cumple o No aplica justificado.
A15: • Cada criterio Cumple tiene evidencia localizable y fecha de validación.
A16: • No existen defectos bloqueantes ni pérdida/inconsistencia de datos.
A17: • Permisos verificados tanto en la interfaz como llamando directamente a la API.
A18: • Operaciones monetarias e inventario reconciliadas con consultas de base de datos.
A19: • Pruebas negativas, concurrencia/reintento y regresión ejecutadas cuando aplican.
A20: • Usuario responsable o cliente valida el flujo y se registra la aceptación.

Sheet Catálogos
A1: CATÁLOGOS Y FUENTES
A4: Estado | B4: Interpretación | D4: Responsables | F4: Fechas rápidas
A5: Pendiente | B5: Aún no se ejecuta | D5: Aaron | F5: 46223
A6: En revisión | B6: Prueba en curso o evidencia por confirmar | D6: David | F6: 46224
A7: Cumple | B7: Resultado esperado alcanzado con evidencia | D7: Mantenimiento | F7: 46225
A8: Parcial | B8: Solo una parte del criterio funciona | F8: 46226
A9: No cumple | B9: Resultado distinto al esperado | F9: 46227
A10: Bloqueado | B10: No puede probarse por dependencia o defecto | F10: 46228
A11: No aplica | B11: Criterio excluido con justificación | F11: 46229
F12: 46230
A13: Fuente | B13: Uso | F13: 46231
A14: Propuesta PDF | B14: Compromiso explícito del documento comercial | F14: 46232
A15: Validación técnica recomendada | B15: Control de calidad necesario para aceptar una implementación profesional | F15: 46233
A16: Propuesta PDF / validar definición con cliente | B16: Alcance mencionado, pero la regla exacta requiere acuerdo | F16: 46234
F17: 46235
A18: Fuente principal: Propuesta_1_Punto_de_Venta_Espanol_Proyecto_Completo_30000.pdf, 7 páginas, creada 2026-08-01. Secciones 1 a 19. | F18: 46236
F19: 46237
F20: 46238
F21: 46239
F22: 46240
F23: 46241
F24: 46242
F25: 46243
F26: 46244
F27: 46245
F28: 46246
F29: 46247
F30: 46248
... F35: 46253
